LICENSE
MANIFEST.in
README.md
requirements.txt
setup.py
deep_teaching_commons/__init__.py
deep_teaching_commons/config.py
deep_teaching_commons/version.py
deep_teaching_commons.egg-info/PKG-INFO
deep_teaching_commons.egg-info/SOURCES.txt
deep_teaching_commons.egg-info/dependency_links.txt
deep_teaching_commons.egg-info/requires.txt
deep_teaching_commons.egg-info/top_level.txt
deep_teaching_commons/data/__init__.py
deep_teaching_commons/data/fundamentals/__init__.py
deep_teaching_commons/data/fundamentals/iris.py
deep_teaching_commons/data/fundamentals/mnist.py
deep_teaching_commons/data/text/__init__.py
deep_teaching_commons/data/text/germ_eval_2014.py
deep_teaching_commons/graphs/__init__.py
deep_teaching_commons/graphs/examples.py
deep_teaching_commons/graphs/visualization.py