Metadata-Version: 1.0
Name: deep-teaching-commons
Version: 0.72
Summary: A Python module for common functionality across notebooks and teaching material.
Home-page: https://gitlab.com/deep.TEACHING/deep-teaching-commons
Author: Christoph Jansen, Benjamin Voigt
Author-email: Christoph.Jansen@htw-berlin.de, Benjamin.Voigt@htw-berlin.de
License: MIT
Platform: any
